{
    "schemaVersion": 2,
    "mediaType": "application/vnd.oci.image.index.v1+json",
    "manifests": [
        {
            "mediaType": "application/vnd.oci.image.manifest.v1+json",
            "digest": "sha256:87eebbac24bd772cd8b3288128aa6caddc0ffd3c7a23f8732daa9bf34f6d66a2",
            "size": 5436,
            "platform": {
                "architecture": "amd64",
                "os": "linux"
            }
        },
        {
            "mediaType": "application/vnd.oci.image.manifest.v1+json",
            "digest": "sha256:babc8c0b1b80c89846646414e11d201b5a42cb36566566608d6b5868ea86cbf8",
            "size": 565,
            "annotations": {
                "vnd.docker.reference.digest": "sha256:87eebbac24bd772cd8b3288128aa6caddc0ffd3c7a23f8732daa9bf34f6d66a2",
                "vnd.docker.reference.type": "attestation-manifest"
            },
            "platform": {
                "architecture": "unknown",
                "os": "unknown"
            }
        },
        {
            "mediaType": "application/vnd.oci.image.manifest.v1+json",
            "digest": "sha256:c71e7a3780d917b8217c17515263d1461ec2bff192660d7dd30cd8889519ebfe",
            "size": 5436,
            "platform": {
                "architecture": "arm64",
                "os": "linux"
            }
        },
        {
            "mediaType": "application/vnd.oci.image.manifest.v1+json",
            "digest": "sha256:6f6b52745bf67d2aec5681068821d69d3028c938a6b1c683c287c9a923eea1ff",
            "size": 565,
            "annotations": {
                "vnd.docker.reference.digest": "sha256:c71e7a3780d917b8217c17515263d1461ec2bff192660d7dd30cd8889519ebfe",
                "vnd.docker.reference.type": "attestation-manifest"
            },
            "platform": {
                "architecture": "unknown",
                "os": "unknown"
            }
        }
    ]
}
